datatools/__init__.py
datatools/__main__.py
datatools/aug/__init__.py
datatools/aug/__main__.py
datatools/aug/bg_changed.py
datatools/aug/imgaugments.py
datatools/dataset/__init__.py
datatools/dataset/coco2voc.py
datatools/dataset/coco_check.py
datatools/dataset/voc2coco.py
datatools/dataset/voc_check.py
datatools/eda/__init__.py
datatools/eda/__main__.py
datatools/eva/__init__.py
datatools/eva/__main__.py
datatools/eva/det/__init__.py
datatools/eva/det/eva.py
datatools/eva/det/utils/__init__.py
datatools/eva/det/utils/options.py
datatools/eva/det/utils/utils.py
datatools/eva/det/utils/voc_xml.py
datatools/split/__init__.py
datatools/split/coco_split.py
datatools/split/voc_split.py
datatools/split/voc_split_dataset.py
datatools/submit/__init__.py
datatools/submit/__main__.py
datatools/submit/platform2xml.py
datatools/submit/xml2platform.py
datatools/trt/__init__.py
datatools/trt/xml2kitti.py
datatools/util/__init__.py
datatools/util/check.py
datatools/util/create_voc_xml.py
datatools/util/datatool_utils.py
datatools/val/__init__.py
datatools/val/__main__.py
examples/__init__.py
examples/datatools/__init__.py
examples/datatools/eva/__init__.py
examples/datatools/eva/det/__init__.py
test/__init__.py
test/test_np.py
test/test_split.py
test/test_unicode.py
test/test_xml.py
test/voc_make_main_txt.py
cspdataset-0.4.8.dist-info/METADATA
cspdataset-0.4.8.dist-info/WHEEL
cspdataset-0.4.8.dist-info/entry_points.txt
cspdataset-0.4.8.dist-info/top_level.txt
cspdataset-0.4.8.dist-info/RECORD
