Metadata-Version: 2.1
Name: cspdataset
Version: 0.4.8
Summary: tools for voc or coco
Home-page: UNKNOWN
Author: xgy
Author-email: example@163.com
License: UNKNOWN
Platform: UNKNOWN
Classifier: Development Status :: 3 - Alpha
Classifier: Programming Language :: Python :: 3
Requires-Dist: requests
Requires-Dist: cPython
Requires-Dist: Cython
Requires-Dist: loguru
Requires-Dist: lxml
Requires-Dist: numpy
Requires-Dist: Pillow
Requires-Dist: pycocotools
Requires-Dist: tqdm
Requires-Dist: opencv-python
